README.md
project/excel/BICAN_schema.xlsx
project/excel/CAP_schema.xlsx
project/excel/general_schema.xlsx
project/graphql/BICAN_schema.graphql
project/graphql/CAP_schema.graphql
project/graphql/general_schema.graphql
project/jsonld/BICAN_schema.context.jsonld
project/jsonld/BICAN_schema.jsonld
project/jsonld/CAP_schema.context.jsonld
project/jsonld/CAP_schema.jsonld
project/jsonld/general_schema.context.jsonld
project/jsonld/general_schema.jsonld
project/jsonschema/BICAN_schema.schema.json
project/jsonschema/CAP_schema.schema.json
project/jsonschema/general_schema.schema.json
project/owl/BICAN_schema.owl.ttl
project/owl/CAP_schema.owl.ttl
project/owl/general_schema.owl.ttl
project/prefixmap/BICAN_schema.yaml
project/prefixmap/CAP_schema.yaml
project/prefixmap/general_schema.yaml
project/protobuf/BICAN_schema.proto
project/protobuf/CAP_schema.proto
project/protobuf/general_schema.proto
project/shacl/BICAN_schema.shacl.ttl
project/shacl/CAP_schema.shacl.ttl
project/shacl/general_schema.shacl.ttl
project/shex/BICAN_schema.shex
project/shex/CAP_schema.shex
project/shex/general_schema.shex
project/sqlschema/BICAN_schema.sql
project/sqlschema/CAP_schema.sql
project/sqlschema/general_schema.sql
cell_annotation_schema/__init__.py
cell_annotation_schema/_version.py
cell_annotation_schema/curie_utils.py
cell_annotation_schema/datamodel/__init__.py
cell_annotation_schema/datamodel/bican/__init__.py
cell_annotation_schema/datamodel/bican/cell_annotation_schema.py
cell_annotation_schema/datamodel/cap/__init__.py
cell_annotation_schema/datamodel/cap/cell_annotation_schema.py
cell_annotation_schema/datamodel/cell_annotation_schema.py
cell_annotation_schema/file_utils.py
cell_annotation_schema/generator/__init__.py
cell_annotation_schema/generator/dataclassgen.py
cell_annotation_schema/legacy/general_schema.json
cell_annotation_schema/ontology/__init__.py
cell_annotation_schema/ontology/data.py
cell_annotation_schema/ontology/dumpers/__init__.py
cas_linkml-0.0.16.dist-info/METADATA
cas_linkml-0.0.16.dist-info/WHEEL
cas_linkml-0.0.16.dist-info/licenses/LICENSE
cas_linkml-0.0.16.dist-info/RECORD
