Metadata-Version: 2.4
Name: cas-linkml
Version: 0.0.16
Summary: General, open-standard schema for cell annotations
License: GNU GPL v3.0
License-File: LICENSE
Author: Huseyin Kir
Author-email: huseyin_kir@yahoo.com
Requires-Python: >=3.9,<4.0
Classifier: License :: Other/Proprietary License
Classifier: Programming Language :: Python :: 3
Classifier: Programming Language :: Python :: 3.9
Classifier: Programming Language :: Python :: 3.10
Classifier: Programming Language :: Python :: 3.11
Classifier: Programming Language :: Python :: 3.12
Classifier: Programming Language :: Python :: 3.13
Classifier: Programming Language :: Python :: 3.14
Provides-Extra: docs
Requires-Dist: dacite (>=1.8.1,<2.0.0)
Requires-Dist: linkml-runtime (>=1.1.24,<2.0.0)
Requires-Dist: oaklib (>=0.6.4,<0.7.0)
Requires-Dist: ruamel-yaml (>=0.18.6,<0.19.0)
Requires-Dist: schema-automator (>=0.5.1,<0.6.0)
